foamlib/__init__.py
foamlib/_cases/__init__.py
foamlib/_cases/_run.py
foamlib/_cases/_subprocess.py
foamlib/_cases/_util.py
foamlib/_cases/async_.py
foamlib/_cases/base.py
foamlib/_cases/slurm.py
foamlib/_cases/sync.py
foamlib/_files/__init__.py
foamlib/_files/_common.py
foamlib/_files/_io.py
foamlib/_files/_parsing/__init__.py
foamlib/_files/_parsing/_parser.py
foamlib/_files/_parsing/exceptions.py
foamlib/_files/_serialization.py
foamlib/_files/_util.py
foamlib/_files/files.py
foamlib/_files/types.py
foamlib/postprocessing/__init__.py
foamlib/postprocessing/load_tables.py
foamlib/postprocessing/table_reader.py
foamlib/preprocessing/__init__.py
foamlib/preprocessing/case_modifier.py
foamlib/preprocessing/grid_parameter_sweep.py
foamlib/preprocessing/of_dict.py
foamlib/preprocessing/parameter_study.py
foamlib/preprocessing/system.py
foamlib/py.typed
foamlib/typing.py
foamlib-1.5.5.dist-info/licenses/LICENSE.txt
foamlib-1.5.5.dist-info/WHEEL
foamlib-1.5.5.dist-info/METADATA
foamlib-1.5.5.dist-info/RECORD
