Metadata-Version: 2.4
Name: foamlib
Version: 1.5.5
Summary: Pythonic interface for working with OpenFOAM
Author: Gabriel S. Gerlero
Author-email: Gabriel S. Gerlero <ggerlero@cimec.unl.edu.ar>
License-Expression: GPL-3.0-only
License-File: LICENSE.txt
Classifier: Development Status :: 5 - Production/Stable
Classifier: Framework :: AsyncIO
Classifier: Intended Audience :: Science/Research
Classifier: Intended Audience :: Developers
Classifier: Operating System :: POSIX
Classifier: Programming Language :: Python :: 3 :: Only
Classifier: Programming Language :: Python :: 3.10
Classifier: Programming Language :: Python :: 3.11
Classifier: Programming Language :: Python :: 3.12
Classifier: Programming Language :: Python :: 3.13
Classifier: Programming Language :: Python :: 3.14
Classifier: Topic :: Scientific/Engineering
Classifier: Topic :: Software Development
Classifier: Typing :: Typed
Requires-Dist: aioshutil>=1,<2
Requires-Dist: multicollections>=1.0.4,<2
Requires-Dist: numpy>=1,<3
Requires-Dist: rich>=13,<15
Requires-Dist: typing-extensions>=4.5,<5 ; python_full_version < '3.13'
Requires-Dist: plotly>=6,<7 ; extra == 'examples'
Requires-Dist: scipy>=1,<2 ; extra == 'examples'
Requires-Dist: foamlib[preprocessing] ; extra == 'examples'
Requires-Dist: foamlib[postprocessing] ; extra == 'examples'
Requires-Dist: pandas>=1,<3 ; extra == 'postprocessing'
Requires-Dist: defusedxml>=0.7.1,<0.8 ; extra == 'postprocessing'
Requires-Dist: pandas>=1,<3 ; extra == 'preprocessing'
Requires-Dist: pydantic>=2.0.0,<3 ; extra == 'preprocessing'
Requires-Python: >=3.10
Project-URL: Documentation, https://foamlib.readthedocs.io
Project-URL: Homepage, https://github.com/gerlero/foamlib
Project-URL: Repository, https://github.com/gerlero/foamlib
Provides-Extra: examples
Provides-Extra: postprocessing
Provides-Extra: preprocessing
